e01loss/__init__.py
e01loss/auxfuncs.py
e01loss/classifylinear.py
e01loss/exact_classify01loss.py
e01loss/test/__init__.py
e01loss/test/test_classify01loss_data.py
e01loss/test/test_classify01loss_synth.py
e01loss/test/voicepath_data.csv
e01loss-1.0.1.dist-info/LICENSE
e01loss-1.0.1.dist-info/METADATA
e01loss-1.0.1.dist-info/WHEEL
e01loss-1.0.1.dist-info/top_level.txt
e01loss-1.0.1.dist-info/RECORD
