Metadata-Version: 2.1
Name: e01loss
Version: 1.0.1
Summary: A Python library for solving the exact 0-1 loss linear classification problem
Home-page: https://github.com/XiHegrt/E01Loss
Author: Xi He
Author-email: xihegrt@gmail.com
License: GNU GPL-3.0
License-File: LICENSE
Requires-Dist: numpy
Requires-Dist: cvxopt
